odoo/addons/pos_config_show_accounting/README.rst
odoo/addons/pos_config_show_accounting/__init__.py
odoo/addons/pos_config_show_accounting/__manifest__.py
odoo/addons/pos_config_show_accounting/i18n/ca.po
odoo/addons/pos_config_show_accounting/i18n/es.po
odoo/addons/pos_config_show_accounting/i18n/pos_config_show_accounting.pot
odoo/addons/pos_config_show_accounting/models/__init__.py
odoo/addons/pos_config_show_accounting/models/pos_config.py
odoo/addons/pos_config_show_accounting/readme/CONTRIBUTORS.rst
odoo/addons/pos_config_show_accounting/readme/DESCRIPTION.rst
odoo/addons/pos_config_show_accounting/readme/USAGE.rst
odoo/addons/pos_config_show_accounting/static/description/icon.png
odoo/addons/pos_config_show_accounting/static/description/index.html
odoo/addons/pos_config_show_accounting/tests/__init__.py
odoo/addons/pos_config_show_accounting/tests/test_pos_config_show_accounting.py
odoo11_addon_pos_config_show_accounting-11.0.1.0.0.99.dev8.dist-info/METADATA
odoo11_addon_pos_config_show_accounting-11.0.1.0.0.99.dev8.dist-info/WHEEL
odoo11_addon_pos_config_show_accounting-11.0.1.0.0.99.dev8.dist-info/top_level.txt
odoo11_addon_pos_config_show_accounting-11.0.1.0.0.99.dev8.dist-info/RECORD
